emoatlas/__init__.py
emoatlas/baselines.py
emoatlas/distributions.py
emoatlas/draw_formamentis_bundling.py
emoatlas/draw_formamentis_force.py
emoatlas/draw_plutchik.py
emoatlas/dyads.py
emoatlas/emo_scores.py
emoatlas/emolib.py
emoatlas/emotions.py
emoatlas/formamentis_edgelist.py
emoatlas/language_dependencies.py
emoatlas/resources.py
emoatlas/textloader.py
emoatlas/antonyms/__init__.py
emoatlas/antonyms/catalan.py
emoatlas/antonyms/chinese.py
emoatlas/antonyms/danish.py
emoatlas/antonyms/dutch.py
emoatlas/antonyms/english.py
emoatlas/antonyms/french.py
emoatlas/antonyms/german.py
emoatlas/antonyms/greek.py
emoatlas/antonyms/italian.py
emoatlas/antonyms/japanese.py
emoatlas/antonyms/lithuanian.py
emoatlas/antonyms/macedonian.py
emoatlas/antonyms/norwegian.py
emoatlas/antonyms/polish.py
emoatlas/antonyms/portuguese.py
emoatlas/antonyms/romanian.py
emoatlas/antonyms/russian.py
emoatlas/antonyms/spanish.py
emoatlas/baseline_tables/english_baseline.dict
emoatlas/baseline_tables/italian_baseline.dict
emoatlas/langs/catalan.json
emoatlas/langs/catalan_idiomatic_tokens.json
emoatlas/langs/chinese.json
emoatlas/langs/chinese_idiomatic_tokens.json
emoatlas/langs/danish.json
emoatlas/langs/danish_idiomatic_tokens.json
emoatlas/langs/danish_stem.json
emoatlas/langs/danish_stem_idiomatic_tokens.json
emoatlas/langs/dutch.json
emoatlas/langs/dutch_idiomatic_tokens.json
emoatlas/langs/dutch_stem.json
emoatlas/langs/dutch_stem_idiomatic_tokens.json
emoatlas/langs/emoji.json
emoatlas/langs/emojis.json
emoatlas/langs/english.json
emoatlas/langs/english_idiomatic_tokens.json
emoatlas/langs/english_stem.json
emoatlas/langs/english_stem_idiomatic_tokens.json
emoatlas/langs/french.json
emoatlas/langs/french_idiomatic_tokens.json
emoatlas/langs/french_stem.json
emoatlas/langs/french_stem_idiomatic_tokens.json
emoatlas/langs/german.json
emoatlas/langs/german_idiomatic_tokens.json
emoatlas/langs/german_stem.json
emoatlas/langs/german_stem_idiomatic_tokens.json
emoatlas/langs/greek.json
emoatlas-0.1.6.dist-info/LICENSE
emoatlas-0.1.6.dist-info/METADATA
emoatlas-0.1.6.dist-info/WHEEL
emoatlas-0.1.6.dist-info/top_level.txt
emoatlas-0.1.6.dist-info/zip-safe
emoatlas-0.1.6.dist-info/RECORD
