Metadata-Version: 2.1
Name: emoatlas
Version: 0.1.6
License-File: LICENSE
Requires-Dist: matplotlib
Requires-Dist: spacy ==3.7.2
Requires-Dist: networkx
Requires-Dist: nltk
Requires-Dist: shapely ==1.8.5.post1
Requires-Dist: pandas
Requires-Dist: community
Requires-Dist: python-louvain
Requires-Dist: numpy
Requires-Dist: setuptools
Requires-Dist: scipy
Requires-Dist: chardet
Requires-Dist: deep-translator
